{
  "minecraft:recipes/decorations/torch": {
    "criteria": {
      "has_stone_pickaxe": "2018-06-14 15:51:50 +0100"
    },
    "done": true
  },
  "minecraft:husbandry/balanced_diet": {
    "criteria": {
      "cooked_chicken": "2018-06-14 15:55:05 +0100"
    },
    "done": false
  },
  "minecraft:husbandry/root": {
    "criteria": {
      "consumed_item": "2018-06-14 15:55:05 +0100"
    },
    "done": true
  },
  "minecraft:recipes/decorations/chest": {
    "criteria": {
      "has_lots_of_items": "2018-06-14 15:52:20 +0100"
    },
    "done": true
  },
  "minecraft:story/upgrade_tools": {
    "criteria": {
      "stone_pickaxe": "2018-06-14 15:51:50 +0100"
    },
    "done": true
  },
  "minecraft:adventure/adventuring_time": {
    "criteria": {
      "plains": "2018-06-14 15:51:51 +0100"
    },
    "done": false
  }
}