{"stat.walkOneCm":47705,"stat.useItem.minecraft.bread":4,"stat.useItem.minecraft.torch":2,"stat.pickup.minecraft.crafting_table":2,"stat.mineBlock.minecraft.cobblestone":1,"stat.craftItem.minecraft.crafting_table":2,"stat.mineBlock.minecraft.double_plant":1,"stat.drop.minecraft.spruce_boat":1,"stat.useItem.minecraft.spruce_boat":2,"stat.mineBlock.minecraft.coal_ore":62,"stat.breakItem.minecraft.stone_pickaxe":1,"stat.pickup.minecraft.log":11,"stat.swimOneCm":7799,"stat.jump":349,"stat.drop.minecraft.skull":1,"stat.pickup.minecraft.coal":60,"stat.fallOneCm":8244,"stat.pickup.minecraft.beef":11,"stat.useItem.minecraft.stone_axe":14,"stat.pickup.minecraft.porkchop":19,"stat.pickup.minecraft.stone":15,"stat.crouchOneCm":6853,"stat.pickup.minecraft.chicken":1,"stat.craftItem.minecraft.torch":24,"stat.pickup.minecraft.dirt":16,"stat.useItem.minecraft.dirt":2,"stat.sprintOneCm":43900,"stat.pickup.minecraft.skull":2,"stat.craftItem.minecraft.stick":12,"stat.craftingTableInteraction":6,"stat.boatOneCm":30142,"stat.craftItem.minecraft.planks":44,"stat.killEntity.Chicken":1,"stat.craftItem.minecraft.spruce_boat":2,"stat.pickup.minecraft.leather":5,"stat.pickup.minecraft.feather":2,"stat.damageTaken":125,"stat.mineBlock.minecraft.crafting_table":3,"stat.craftItem.minecraft.stone_pickaxe":1,"stat.mobKills":21,"stat.pickup.minecraft.cobblestone":57,"stat.mineBlock.minecraft.log":11,"stat.useItem.minecraft.stone_shovel":15,"stat.pickup.minecraft.reeds":14,"stat.flyOneCm":58975,"stat.drop":2,"stat.mineBlock.minecraft.leaves":1,"stat.playOneMinute":36000,"stat.killEntity.Sheep":3,"stat.useItem.minecraft.stone_pickaxe":162,"stat.sneakTime":3680,"stat.useItem.minecraft.stone_sword":52,"stat.pickup.minecraft.wool":3,"stat.damageDealt":1950,"stat.pickup.minecraft.spruce_boat":2,"stat.timeSinceDeath":36000,"stat.killEntity.Cow":6,"stat.mineBlock.minecraft.dirt":14,"stat.useItem.minecraft.crafting_table":3,"stat.mineBlock.minecraft.stone":99,"stat.killEntity.Pig":11,"stat.mineBlock.minecraft.tallgrass":5,"stat.pickup.minecraft.mutton":5,"stat.diveOneCm":11953}