{"stat.walkOneCm":27716,"stat.useItem.minecraft.bread":2,"stat.boatOneCm":6101,"stat.craftItem.minecraft.planks":20,"stat.killEntity.Chicken":1,"stat.craftItem.minecraft.spruce_boat":2,"stat.pickup.minecraft.crafting_table":1,"stat.pickup.minecraft.leather":3,"stat.pickup.minecraft.feather":2,"stat.damageTaken":125,"stat.mineBlock.minecraft.crafting_table":1,"stat.craftItem.minecraft.crafting_table":1,"stat.mineBlock.minecraft.double_plant":1,"stat.drop.minecraft.spruce_boat":1,"stat.mobKills":6,"stat.useItem.minecraft.spruce_boat":1,"stat.mineBlock.minecraft.log":5,"stat.useItem.minecraft.stone_shovel":6,"stat.pickup.minecraft.log":5,"stat.flyOneCm":37145,"stat.drop":2,"stat.jump":191,"stat.swimOneCm":110,"stat.mineBlock.minecraft.leaves":1,"stat.drop.minecraft.skull":1,"stat.playOneMinute":24000,"stat.fallOneCm":4658,"stat.pickup.minecraft.beef":3,"stat.killEntity.Sheep":3,"stat.sneakTime":469,"stat.useItem.minecraft.stone_sword":16,"stat.pickup.minecraft.wool":3,"stat.useItem.minecraft.stone_axe":6,"stat.damageDealt":470,"stat.crouchOneCm":1910,"stat.pickup.minecraft.chicken":1,"stat.timeSinceDeath":24000,"stat.pickup.minecraft.dirt":5,"stat.killEntity.Cow":2,"stat.mineBlock.minecraft.dirt":5,"stat.sprintOneCm":27266,"stat.useItem.minecraft.crafting_table":1,"stat.mineBlock.minecraft.tallgrass":4,"stat.pickup.minecraft.mutton":5,"stat.pickup.minecraft.skull":1,"stat.craftingTableInteraction":4}