{"stat.craftItem.minecraft.stone_shovel":1,"stat.walkOneCm":103929,"stat.craftItem.minecraft.bed":1,"stat.pickup.minecraft.bone":2,"stat.useItem.minecraft.torch":1,"stat.leaveGame":1,"stat.pickup.minecraft.stone_pickaxe":1,"stat.useItem.minecraft.cobblestone":5,"stat.pickup.minecraft.stone_axe":1,"stat.craftItem.minecraft.crafting_table":1,"stat.furnaceInteraction":1,"stat.killEntity.Wolf":1,"stat.pickup.minecraft.leather_chestplate":1,"stat.mineBlock.minecraft.coal_ore":35,"stat.pickup.minecraft.string":4,"stat.pickup.minecraft.log":11,"stat.swimOneCm":1064,"stat.jump":472,"stat.pickup.minecraft.cooked_chicken":59,"stat.pickup.minecraft.coal":35,"stat.fallOneCm":15187,"stat.useItem.minecraft.stone_axe":23,"stat.crouchOneCm":787,"stat.pickup.minecraft.leather_helmet":1,"stat.craftItem.minecraft.torch":4,"stat.pickup.minecraft.sapling":1,"stat.pickup.minecraft.dirt":17,"stat.sprintOneCm":76558,"stat.useItem.minecraft.cooked_chicken":8,"stat.craftItem.minecraft.stick":4,"stat.craftingTableInteraction":4,"stat.pickup.minecraft.rotten_flesh":12,"stat.killEntity.Skeleton":1,"stat.pickup.minecraft.stone_shovel":2,"stat.craftItem.minecraft.furnace":1,"stat.useItem.minecraft.bed":1,"stat.craftItem.minecraft.planks":44,"stat.craftItem.minecraft.stone_axe":1,"stat.damageTaken":715,"stat.killEntity.Spider":1,"stat.pickup.minecraft.stone_sword":1,"stat.craftItem.minecraft.stone_pickaxe":1,"stat.pickup.minecraft.written_book":1,"stat.useItem.minecraft.furnace":1,"stat.mobKills":26,"stat.pickup.minecraft.cobblestone":50,"stat.pickup.minecraft.leather_leggings":1,"stat.pickup.minecraft.leather_boots":1,"stat.mineBlock.minecraft.log":11,"stat.craftItem.minecraft.wooden_door":3,"stat.useItem.minecraft.stone_shovel":17,"stat.useItem.minecraft.wooden_door":2,"stat.craftItem.minecraft.stone_sword":1,"stat.flyOneCm":90973,"stat.deaths":1,"stat.pickup.minecraft.wheat_seeds":2,"stat.mineBlock.minecraft.leaves":4,"stat.playOneMinute":30646,"stat.killEntity.Sheep":14,"stat.useItem.minecraft.stone_pickaxe":87,"stat.sneakTime":200,"stat.useItem.minecraft.stone_sword":87,"stat.pickup.minecraft.wool":15,"stat.damageDealt":3066,"stat.killEntity.Zombie":8,"stat.timeSinceDeath":21595,"stat.mineBlock.minecraft.dirt":17,"stat.useItem.minecraft.crafting_table":1,"stat.mineBlock.minecraft.stone":51,"stat.mineBlock.minecraft.tallgrass":10,"stat.pickup.minecraft.mutton":24}